ioscheduler/__init__.py
ioscheduler/ioscheduler.py
ioscheduler-0.0.1.dist-info/LICENSE
ioscheduler-0.0.1.dist-info/METADATA
ioscheduler-0.0.1.dist-info/WHEEL
ioscheduler-0.0.1.dist-info/top_level.txt
ioscheduler-0.0.1.dist-info/RECORD
